Metadata-Version: 2.1
Name: ml-snippets
Version: 1.0.0
Summary: snippets lib
Author: Kouros Basiri
Author-email: kouros.basiri@gmail.com
Keywords: Snippets,Data Science,ML
Classifier: Natural Language :: English
Classifier: Programming Language :: Python
Classifier: Programming Language :: Python :: 3
Classifier: Programming Language :: Python :: 3.6
Classifier: Programming Language :: Python :: 3.7
Classifier: Programming Language :: Python :: 3.8
Classifier: Programming Language :: Python :: 3.9
Classifier: Topic :: Software Development
Requires-Python: >= 3.6
